basistheory/__init__.py
basistheory/api_client.py
basistheory/configuration.py
basistheory/exceptions.py
basistheory/model_utils.py
basistheory/request_options.py
basistheory/rest.py
basistheory/api/__init__.py
basistheory/api/application_keys_api.py
basistheory/api/application_templates_api.py
basistheory/api/applications_api.py
basistheory/api/detokenize_api.py
basistheory/api/enrichments_api.py
basistheory/api/logs_api.py
basistheory/api/permissions_api.py
basistheory/api/proxies_api.py
basistheory/api/reactor_formulas_api.py
basistheory/api/reactors_api.py
basistheory/api/roles_api.py
basistheory/api/sessions_api.py
basistheory/api/tenants_api.py
basistheory/api/three_ds_api.py
basistheory/api/tokenize_api.py
basistheory/api/tokens_api.py
basistheory/apis/__init__.py
basistheory/model/__init__.py
basistheory/model/access_rule.py
basistheory/model/application.py
basistheory/model/application_key.py
basistheory/model/application_paginated_list.py
basistheory/model/application_template.py
basistheory/model/authenticate_three_ds_session_request.py
basistheory/model/authorize_session_request.py
basistheory/model/bank_verification_request.py
basistheory/model/basis_theory_error.py
basistheory/model/bin_details.py
basistheory/model/bin_details_bank.py
basistheory/model/bin_details_country.py
basistheory/model/bin_details_product.py
basistheory/model/card_details.py
basistheory/model/condition.py
basistheory/model/create_application_request.py
basistheory/model/create_proxy_request.py
basistheory/model/create_reactor_formula_request.py
basistheory/model/create_reactor_request.py
basistheory/model/create_session_response.py
basistheory/model/create_tenant_connection_request.py
basistheory/model/create_tenant_connection_response.py
basistheory/model/create_tenant_invitation_request.py
basistheory/model/create_three_ds_session_request.py
basistheory/model/create_three_ds_session_response.py
basistheory/model/create_token_request.py
basistheory-3.0.0.dist-info/LICENSE
basistheory-3.0.0.dist-info/METADATA
basistheory-3.0.0.dist-info/WHEEL
basistheory-3.0.0.dist-info/top_level.txt
basistheory-3.0.0.dist-info/RECORD
