Metadata-Version: 2.1
Name: basistheory
Version: 3.0.0
Summary: BasisTheory Python SDK
Home-page: https://basistheory.com
Author: Basis Theory
Author-email: support@basistheory.com
License: UNKNOWN
Project-URL: Documentation, https://docs.basistheory.com/
Project-URL: Source Code, https://github.com/Basis-Theory/basistheory-python
Keywords: BasisTheory,Basis Theory,SDK,Python
Platform: UNKNOWN
Requires-Python: >=3.7
Requires-Dist: urllib3>=1.25.3
Requires-Dist: python-dateutil
